streamlit_azure_login/__init__.py
streamlit_azure_login/frontend/build/asset-manifest.json
streamlit_azure_login/frontend/build/favicon.ico
streamlit_azure_login/frontend/build/index.html
streamlit_azure_login/frontend/build/manifest.json
streamlit_azure_login/frontend/build/precache-manifest.d5e1ae1749af086ccb44d07bf3c2a214.js
streamlit_azure_login/frontend/build/service-worker.js
streamlit_azure_login/frontend/build/static/css/main.fab8f5c4.chunk.css
streamlit_azure_login/frontend/build/static/css/main.fab8f5c4.chunk.css.map
streamlit_azure_login/frontend/build/static/js/2.4c20aea0.chunk.js
streamlit_azure_login/frontend/build/static/js/2.4c20aea0.chunk.js.LICENSE.txt
streamlit_azure_login/frontend/build/static/js/2.4c20aea0.chunk.js.map
streamlit_azure_login/frontend/build/static/js/main.74c711e3.chunk.js
streamlit_azure_login/frontend/build/static/js/main.74c711e3.chunk.js.map
streamlit_azure_login/frontend/build/static/js/runtime-main.a145a3b2.js
streamlit_azure_login/frontend/build/static/js/runtime-main.a145a3b2.js.map
streamlit_azure_ad_login-0.1.2.dist-info/LICENSE
streamlit_azure_ad_login-0.1.2.dist-info/METADATA
streamlit_azure_ad_login-0.1.2.dist-info/WHEEL
streamlit_azure_ad_login-0.1.2.dist-info/top_level.txt
streamlit_azure_ad_login-0.1.2.dist-info/RECORD
