Metadata-Version: 2.1
Name: streamlit-azure-ad-login
Version: 0.1.2
Summary: Python package to use a login with Azure AD
Home-page: UNKNOWN
Author: Juan Huarte, Ramiro Gallo
License: UNKNOWN
Platform: UNKNOWN
Requires-Python: >=3.6
License-File: LICENSE
Requires-Dist: streamlit (>=0.85.1)
